page_screenshot
