Metadata-Version: 1.1
Name: page-screenshot
Version: 0.0.3
Summary: a complete capture from a web page
Home-page: https://github.com/xiaohong2019/page_screenshot
Author: xiaohong2019
Author-email: 2229009854@qq.com
License: UNKNOWN
Platform: UNKNOWN
Classifier: Intended Audience :: Developers
Classifier: Programming Language :: Python :: 3.6
Classifier: License :: OSI Approved :: Apache Software License
Classifier: Operating System :: Microsoft :: Windows
